easy_edge.py
easy_edge-0.1.3.dist-info/METADATA
easy_edge-0.1.3.dist-info/WHEEL
easy_edge-0.1.3.dist-info/entry_points.txt
easy_edge-0.1.3.dist-info/top_level.txt
easy_edge-0.1.3.dist-info/RECORD
