Metadata-Version: 2.4
Name: easy-edge
Version: 0.1.3
Summary: A simple Ollama-like tool for running LLMs locally
Home-page: https://github.com/criminact/easy-edge
Author: Easy Edge Team
Project-URL: Source, https://github.com/criminact/easy-edge
Project-URL: Tracker, https://github.com/criminact/easy-edge/issues
Classifier: Programming Language :: Python :: 3
Classifier: License :: OSI Approved :: MIT License
Classifier: Operating System :: OS Independent
Classifier: Intended Audience :: End Users/Desktop
Classifier: Environment :: Console
Classifier: Topic :: Software Development :: Libraries :: Application Frameworks
Classifier: Topic :: Utilities
Requires-Python: >=3.9.6
Requires-Dist: accelerate==1.8.1
Requires-Dist: aiohappyeyeballs==2.6.1
Requires-Dist: aiohttp==3.12.14
Requires-Dist: aiosignal==1.4.0
Requires-Dist: async-timeout==5.0.1
Requires-Dist: attrs==25.3.0
Requires-Dist: bitsandbytes
Requires-Dist: certifi==2025.7.14
Requires-Dist: charset-normalizer==3.4.2
Requires-Dist: click==8.1.7
Requires-Dist: datasets==4.0.0
Requires-Dist: dill==0.3.8
Requires-Dist: diskcache==5.6.3
Requires-Dist: filelock==3.18.0
Requires-Dist: frozenlist==1.7.0
Requires-Dist: fsspec==2025.3.0
Requires-Dist: hf-xet==1.1.5
Requires-Dist: huggingface-hub==0.33.4
Requires-Dist: idna==3.10
Requires-Dist: Jinja2==3.1.6
Requires-Dist: llama_cpp_python==0.3.12
Requires-Dist: markdown-it-py==3.0.0
Requires-Dist: MarkupSafe==3.0.2
Requires-Dist: mdurl==0.1.2
Requires-Dist: mpmath==1.3.0
Requires-Dist: multidict==6.6.3
Requires-Dist: multiprocess==0.70.16
Requires-Dist: networkx==3.2.1
Requires-Dist: numpy==2.0.2
Requires-Dist: packaging==25.0
Requires-Dist: pandas==2.3.1
Requires-Dist: peft==0.16.0
Requires-Dist: pillow==11.3.0
Requires-Dist: propcache==0.3.2
Requires-Dist: psutil==7.0.0
Requires-Dist: pyarrow==20.0.0
Requires-Dist: Pygments==2.19.2
Requires-Dist: python-dateutil==2.9.0.post0
Requires-Dist: pytz==2025.2
Requires-Dist: PyYAML==6.0.2
Requires-Dist: regex==2024.11.6
Requires-Dist: requests==2.32.4
Requires-Dist: rich==13.7.0
Requires-Dist: safetensors==0.5.3
Requires-Dist: scipy==1.13.1
Requires-Dist: six==1.17.0
Requires-Dist: sympy==1.14.0
Requires-Dist: tokenizers==0.21.2
Requires-Dist: torch
Requires-Dist: torchaudio==2.7.1
Requires-Dist: torchvision==0.22.1
Requires-Dist: tqdm==4.67.1
Requires-Dist: transformers==4.53.2
Requires-Dist: typing_extensions==4.14.1
Requires-Dist: tzdata==2025.2
Requires-Dist: urllib3==2.5.0
Requires-Dist: xxhash==3.5.0
Requires-Dist: yarl==1.20.1
Requires-Dist: sentencepiece~=0.2.0
Requires-Dist: gguf>=0.1.0
Requires-Dist: protobuf<5.0.0,>=4.21.0
Dynamic: author
Dynamic: classifier
Dynamic: description
Dynamic: description-content-type
Dynamic: home-page
Dynamic: project-url
Dynamic: requires-dist
Dynamic: requires-python
Dynamic: summary
